Metadata-Version: 1.0
Name: jsonext
Version: 0.4.2
Summary: Well-structured helpers to help serializing commonly encountered structures to JSON (like datetime, to_dict(),  etc.
Home-page: http://github.com/mbr/jsonext
Author: Marc Brinkmann
Author-email: git@marcbrinkmann.de
License: MIT
Platform: UNKNOWN
